{
  "tables": {
    "archived_flows": {
      "fields": [
        [
          "branch_id",
          "uuid",
          false
        ],
        [
          "created_at",
          "timestamp",
          false
        ],
        [
          "id",
          "uuid",
          false
        ],
        [
          "node_id",
          "uuid",
          false
        ],
        [
          "start_index",
          "int",
          false
        ],
        [
          "title",
          "text",
          false
        ],
        [
          "updated_at",
          "timestamp",
          false
        ],
        [
          "vertical_index",
          "double",
          false
        ]
      ],
      "field_names": [
        "node_id",
        "branch_id",
        "updated_at",
        "id",
        "created_at",
        "start_index",
        "title",
        "vertical_index"
      ],
      "types_by_name": {
        "created_at": "timestamp",
        "updated_at": "timestamp",
        "start_index": "int",
        "branch_id": "uuid",
        "id": "uuid",
        "node_id": "uuid",
        "title": "text",
        "vertical_index": "double"
      },
      "type_name": "",
      "table_name": "",
      "base_table": "",
      "partition_keys": [
        "branch_id"
      ],
      "clustering_keys": [
        "id",
        "node_id",
        "start_index",
        "vertical_index"
      ],
      "static_columns": [],
      "global_secondary_indexes": [],
      "local_secondary_indexes": [
        [
          "archived_flows_branch_id_id_idx",
          "id"
        ]
      ],
      "table_options": null
    },
    "branches": {
      "fields": [
        [
          "conflict",
          "frozen<conflict>",
          false
        ],
        [
          "created_flow_step_inputs_by_node",
          "map<uuid, frozen<map<uuid, frozen<set<uuid>>>>>",
          false
        ],
        [
          "created_flow_step_nodes",
          "map<uuid, frozen<set<uuid>>>",
          false
        ],
        [
          "created_flow_step_outputs_by_node",
          "map<uuid, frozen<map<uuid, frozen<set<uuid>>>>>",
          false
        ],
        [
          "created_flow_steps",
          "set<uuid>",
          false
        ],
        [
          "created_flows",
          "set<uuid>",
          false
        ],
        [
          "created_ios",
          "set<uuid>",
          false
        ],
        [
          "created_nodes",
          "set<uuid>",
          false
        ],
        [
          "created_workflow_initial_inputs",
          "map<uuid, frozen<list<uuid>>>",
          false
        ],
        [
          "deleted_flow_step_inputs_by_node",
          "map<uuid, frozen<map<uuid, frozen<set<uuid>>>>>",
          false
        ],
        [
          "deleted_flow_step_nodes",
          "map<uuid, frozen<set<uuid>>>",
          false
        ],
        [
          "deleted_flow_step_outputs_by_node",
          "map<uuid, frozen<map<uuid, frozen<set<uuid>>>>>",
          false
        ],
        [
          "deleted_flow_steps",
          "set<uuid>",
          false
        ],
        [
          "deleted_flows",
          "set<uuid>",
          false
        ],
        [
          "deleted_ios",
          "set<uuid>",
          false
        ],
        [
          "deleted_nodes",
          "set<uuid>",
          false
        ],
        [
          "deleted_workflow_initial_inputs",
          "map<uuid, frozen<list<uuid>>>",
          false
        ],
        [
          "description",
          "text",
          false
        ],
        [
          "description_change_by_object",
          "frozen<map<uuid, frozen<textchange>>>",
          false
        ],
        [
          "edited_description_flow_steps",
          "set<uuid>",
          false
        ],
        [
          "edited_description_flows",
          "set<uuid>",
          false
        ],
        [
          "edited_description_ios",
          "set<uuid>",
          false
        ],
        [
          "edited_description_nodes",
          "set<uuid>",
          false
        ],
        [
          "edited_nodes",
          "set<uuid>",
          false
        ],
        [
          "edited_title_flows",
          "set<uuid>",
          false
        ],
        [
          "edited_title_ios",
          "set<uuid>",
          false
        ],
        [
          "edited_title_nodes",
          "set<uuid>",
          false
        ],
        [
          "editor_ids",
          "set<uuid>",
          false
        ],
        [
          "id",
          "uuid",
          false
        ],
        [
          "is_contribution_request",
          "boolean",
          false
        ],
        [
          "is_public",
          "boolean",
          false
        ],
        [
          "kept_flow_steps",
          "set<uuid>",
          false
        ],
        [
          "node_id",
          "uuid",
          false
        ],
        [
          "owner",
          "frozen<profile>",
          false
        ],
        [
          "owner_id",
          "uuid",
          false
        ],
        [
          "reordered_nodes",
          "list<frozen<branchreorderdata>>",
          false
        ],
        [
          "restored_flow_steps",
          "set<uuid>",
          false
        ],
        [
          "restored_flows",
          "set<uuid>",
          false
        ],
        [
          "restored_ios",
          "set<uuid>",
          false
        ],
        [
          "restored_nodes",
          "set<uuid>",
          false
        ],
        [
          "root_id",
          "uuid",
          false
        ],
        [
          "status",
          "text",
          false
        ],
        [
          "title",
          "text",
          false
        ],
        [
          "title_change_by_object",
          "frozen<map<uuid, frozen<textchange>>>",
          false
        ],
        [
          "viewer_ids",
          "set<uuid>",
          false
        ]
      ],
      "field_names": [
        "restored_flow_steps",
        "root_id",
        "viewer_ids",
        "id",
        "status",
        "deleted_ios",
        "title",
        "edited_description_ios",
        "title_change_by_object",
        "created_flow_steps",
        "editor_ids",
        "edited_description_flows",
        "is_contribution_request",
        "restored_nodes",
        "deleted_flow_step_inputs_by_node",
        "description",
        "created_ios",
        "edited_description_nodes",
        "is_public",
        "owner",
        "restored_flows",
        "edited_description_flow_steps",
        "deleted_nodes",
        "edited_title_nodes",
        "created_nodes",
        "owner_id",
        "created_flow_step_outputs_by_node",
        "edited_nodes",
        "reordered_nodes",
        "deleted_workflow_initial_inputs",
        "restored_ios",
        "edited_title_ios",
        "created_flow_step_inputs_by_node",
        "deleted_flows",
        "created_flows",
        "edited_title_flows",
        "conflict",
        "deleted_flow_step_outputs_by_node",
        "created_workflow_initial_inputs",
        "deleted_flow_step_nodes",
        "description_change_by_object",
        "deleted_flow_steps",
        "created_flow_step_nodes",
        "kept_flow_steps",
        "node_id"
      ],
      "types_by_name": {
        "restored_flow_steps": "set<uuid>",
        "is_contribution_request": "boolean",
        "reordered_nodes": "list<frozen<branchreorderdata>>",
        "edited_title_nodes": "set<uuid>",
        "edited_description_nodes": "set<uuid>",
        "restored_ios": "set<uuid>",
        "description_change_by_object": "frozen<map<uuid, frozen<textchange>>>",
        "title_change_by_object": "frozen<map<uuid, frozen<textchange>>>",
        "created_flows": "set<uuid>",
        "title": "text",
        "deleted_flow_step_inputs_by_node": "map<uuid, frozen<map<uuid, frozen<set<uuid>>>>>",
        "id": "uuid",
        "restored_nodes": "set<uuid>",
        "is_public": "boolean",
        "root_id": "uuid",
        "edited_description_ios": "set<uuid>",
        "created_flow_step_inputs_by_node": "map<uuid, frozen<map<uuid, frozen<set<uuid>>>>>",
        "created_nodes": "set<uuid>",
        "owner": "frozen<profile>",
        "owner_id": "uuid",
        "created_flow_step_nodes": "map<uuid, frozen<set<uuid>>>",
        "conflict": "frozen<conflict>",
        "created_flow_steps": "set<uuid>",
        "editor_ids": "set<uuid>",
        "restored_flows": "set<uuid>",
        "created_flow_step_outputs_by_node": "map<uuid, frozen<map<uuid, frozen<set<uuid>>>>>",
        "edited_description_flows": "set<uuid>",
        "deleted_flow_step_nodes": "map<uuid, frozen<set<uuid>>>",
        "node_id": "uuid",
        "edited_title_flows": "set<uuid>",
        "created_ios": "set<uuid>",
        "deleted_flows": "set<uuid>",
        "status": "text",
        "created_workflow_initial_inputs": "map<uuid, frozen<list<uuid>>>",
        "deleted_nodes": "set<uuid>",
        "edited_nodes": "set<uuid>",
        "edited_description_flow_steps": "set<uuid>",
        "deleted_flow_steps": "set<uuid>",
        "deleted_ios": "set<uuid>",
        "edited_title_ios": "set<uuid>",
        "deleted_workflow_initial_inputs": "map<uuid, frozen<list<uuid>>>",
        "kept_flow_steps": "set<uuid>",
        "viewer_ids": "set<uuid>",
        "description": "text",
        "deleted_flow_step_outputs_by_node": "map<uuid, frozen<map<uuid, frozen<set<uuid>>>>>"
      },
      "type_name": "",
      "table_name": "",
      "base_table": "",
      "partition_keys": [
        "id"
      ],
      "clustering_keys": [],
      "static_columns": [],
      "global_secondary_indexes": [],
      "local_secondary_indexes": [],
      "table_options": null
    },
    "input_outputs": {
      "fields": [
        [
          "branch_id",
          "uuid",
          false
        ],
        [
          "created_at",
          "timestamp",
          false
        ],
        [
          "data_type",
          "text",
          false
        ],
        [
          "flow_id",
          "uuid",
          false
        ],
        [
          "flow_step_id",
          "uuid",
          false
        ],
        [
          "id",
          "uuid",
          false
        ],
        [
          "initial_input",
          "boolean",
          false
        ],
        [
          "inputted_by_flow_steps",
          "set<uuid>",
          false
        ],
        [
          "main_id",
          "uuid",
          false
        ],
        [
          "node_id",
          "uuid",
          false
        ],
        [
          "root_id",
          "uuid",
          false
        ],
        [
          "title",
          "text",
          false
        ],
        [
          "unit",
          "text",
          false
        ],
        [
          "updated_at",
          "timestamp",
          false
        ],
        [
          "value",
          "text",
          false
        ]
      ],
      "field_names": [
        "id",
        "title",
        "value",
        "inputted_by_flow_steps",
        "flow_step_id",
        "node_id",
        "root_id",
        "initial_input",
        "created_at",
        "updated_at",
        "flow_id",
        "branch_id",
        "main_id",
        "data_type",
        "unit"
      ],
      "types_by_name": {
        "flow_id": "uuid",
        "title": "text",
        "root_id": "uuid",
        "branch_id": "uuid",
        "id": "uuid",
        "data_type": "text",
        "node_id": "uuid",
        "main_id": "uuid",
        "created_at": "timestamp",
        "updated_at": "timestamp",
        "unit": "text",
        "inputted_by_flow_steps": "set<uuid>",
        "flow_step_id": "uuid",
        "initial_input": "boolean",
        "value": "text"
      },
      "type_name": "",
      "table_name": "",
      "base_table": "",
      "partition_keys": [
        "branch_id"
      ],
      "clustering_keys": [
        "id",
        "root_id"
      ],
      "static_columns": [],
      "global_secondary_indexes": [],
      "local_secondary_indexes": [
        [
          "input_outputs_branch_id_main_id_idx",
          "main_id"
        ],
        [
          "input_outputs_branch_id_node_id_idx",
          "node_id"
        ]
      ],
      "table_options": null
    },
    "invitations": {
      "fields": [
        [
          "branch_id",
          "uuid",
          false
        ],
        [
          "created_at",
          "timestamp",
          false
        ],
        [
          "expires_at",
          "timestamp",
          false
        ],
        [
          "inviter_id",
          "uuid",
          false
        ],
        [
          "node_id",
          "uuid",
          false
        ],
        [
          "status",
          "text",
          false
        ],
        [
          "updated_at",
          "timestamp",
          false
        ],
        [
          "username_or_email",
          "text",
          false
        ]
      ],
      "field_names": [
        "node_id",
        "created_at",
        "username_or_email",
        "expires_at",
        "branch_id",
        "inviter_id",
        "status",
        "updated_at"
      ],
      "types_by_name": {
        "branch_id": "uuid",
        "created_at": "timestamp",
        "expires_at": "timestamp",
        "status": "text",
        "inviter_id": "uuid",
        "node_id": "uuid",
        "updated_at": "timestamp",
        "username_or_email": "text"
      },
      "type_name": "",
      "table_name": "",
      "base_table": "",
      "partition_keys": [
        "branch_id"
      ],
      "clustering_keys": [
        "node_id",
        "username_or_email"
      ],
      "static_columns": [],
      "global_secondary_indexes": [],
      "local_secondary_indexes": [],
      "table_options": null
    },
    "commits": {
      "fields": [
        [
          "branch_id",
          "uuid",
          false
        ],
        [
          "commit_type",
          "text",
          false
        ],
        [
          "created_at",
          "timestamp",
          false
        ],
        [
          "data",
          "text",
          false
        ],
        [
          "id",
          "uuid",
          false
        ],
        [
          "node_id",
          "uuid",
          false
        ],
        [
          "object_id",
          "uuid",
          false
        ]
      ],
      "field_names": [
        "data",
        "commit_type",
        "branch_id",
        "node_id",
        "object_id",
        "id",
        "created_at"
      ],
      "types_by_name": {
        "data": "text",
        "branch_id": "uuid",
        "created_at": "timestamp",
        "id": "uuid",
        "node_id": "uuid",
        "object_id": "uuid",
        "commit_type": "text"
      },
      "type_name": "",
      "table_name": "",
      "base_table": "",
      "partition_keys": [
        "branch_id"
      ],
      "clustering_keys": [
        "id",
        "node_id"
      ],
      "static_columns": [],
      "global_secondary_indexes": [],
      "local_secondary_indexes": [],
      "table_options": null
    },
    "archived_input_outputs": {
      "fields": [
        [
          "branch_id",
          "uuid",
          false
        ],
        [
          "created_at",
          "timestamp",
          false
        ],
        [
          "data_type",
          "text",
          false
        ],
        [
          "flow_id",
          "uuid",
          false
        ],
        [
          "flow_step_id",
          "uuid",
          false
        ],
        [
          "id",
          "uuid",
          false
        ],
        [
          "inputted_by_flow_steps",
          "set<uuid>",
          false
        ],
        [
          "main_id",
          "uuid",
          false
        ],
        [
          "node_id",
          "uuid",
          false
        ],
        [
          "root_id",
          "uuid",
          false
        ],
        [
          "title",
          "text",
          false
        ],
        [
          "unit",
          "text",
          false
        ],
        [
          "updated_at",
          "timestamp",
          false
        ],
        [
          "value",
          "text",
          false
        ]
      ],
      "field_names": [
        "updated_at",
        "flow_id",
        "value",
        "id",
        "inputted_by_flow_steps",
        "main_id",
        "node_id",
        "unit",
        "created_at",
        "branch_id",
        "data_type",
        "flow_step_id",
        "root_id",
        "title"
      ],
      "types_by_name": {
        "branch_id": "uuid",
        "inputted_by_flow_steps": "set<uuid>",
        "data_type": "text",
        "main_id": "uuid",
        "flow_id": "uuid",
        "title": "text",
        "updated_at": "timestamp",
        "created_at": "timestamp",
        "id": "uuid",
        "flow_step_id": "uuid",
        "root_id": "uuid",
        "node_id": "uuid",
        "unit": "text",
        "value": "text"
      },
      "type_name": "",
      "table_name": "",
      "base_table": "",
      "partition_keys": [
        "branch_id"
      ],
      "clustering_keys": [
        "id",
        "root_id"
      ],
      "static_columns": [],
      "global_secondary_indexes": [],
      "local_secondary_indexes": [],
      "table_options": null
    },
    "nodes": {
      "fields": [
        [
          "ancestor_ids",
          "set<uuid>",
          false
        ],
        [
          "branch_id",
          "uuid",
          false
        ],
        [
          "cover_image_filename",
          "text",
          false
        ],
        [
          "cover_image_url",
          "text",
          false
        ],
        [
          "created_at",
          "timestamp",
          false
        ],
        [
          "editor_ids",
          "set<uuid>",
          false
        ],
        [
          "id",
          "uuid",
          false
        ],
        [
          "is_public",
          "boolean",
          false
        ],
        [
          "is_root",
          "boolean",
          false
        ],
        [
          "order_index",
          "double",
          false
        ],
        [
          "owner",
          "frozen<profile>",
          false
        ],
        [
          "owner_id",
          "uuid",
          false
        ],
        [
          "parent_id",
          "uuid",
          false
        ],
        [
          "root_id",
          "uuid",
          false
        ],
        [
          "title",
          "text",
          false
        ],
        [
          "updated_at",
          "timestamp",
          false
        ],
        [
          "viewer_ids",
          "set<uuid>",
          false
        ]
      ],
      "field_names": [
        "is_root",
        "created_at",
        "id",
        "owner",
        "owner_id",
        "parent_id",
        "title",
        "viewer_ids",
        "cover_image_url",
        "root_id",
        "editor_ids",
        "ancestor_ids",
        "branch_id",
        "cover_image_filename",
        "is_public",
        "updated_at",
        "order_index"
      ],
      "types_by_name": {
        "editor_ids": "set<uuid>",
        "cover_image_filename": "text",
        "updated_at": "timestamp",
        "ancestor_ids": "set<uuid>",
        "branch_id": "uuid",
        "is_root": "boolean",
        "order_index": "double",
        "viewer_ids": "set<uuid>",
        "created_at": "timestamp",
        "is_public": "boolean",
        "root_id": "uuid",
        "id": "uuid",
        "title": "text",
        "cover_image_url": "text",
        "owner": "frozen<profile>",
        "parent_id": "uuid",
        "owner_id": "uuid"
      },
      "type_name": "",
      "table_name": "",
      "base_table": "",
      "partition_keys": [
        "branch_id"
      ],
      "clustering_keys": [
        "id"
      ],
      "static_columns": [],
      "global_secondary_indexes": [],
      "local_secondary_indexes": [],
      "table_options": null
    },
    "attachments": {
      "fields": [
        [
          "branch_id",
          "uuid",
          false
        ],
        [
          "created_at",
          "timestamp",
          false
        ],
        [
          "id",
          "uuid",
          false
        ],
        [
          "key",
          "text",
          false
        ],
        [
          "node_id",
          "uuid",
          false
        ],
        [
          "object_id",
          "uuid",
          false
        ],
        [
          "root_id",
          "uuid",
          false
        ],
        [
          "updated_at",
          "timestamp",
          false
        ],
        [
          "url",
          "text",
          false
        ],
        [
          "user_id",
          "uuid",
          false
        ]
      ],
      "field_names": [
        "url",
        "user_id",
        "branch_id",
        "id",
        "key",
        "updated_at",
        "node_id",
        "root_id",
        "created_at",
        "object_id"
      ],
      "types_by_name": {
        "root_id": "uuid",
        "created_at": "timestamp",
        "node_id": "uuid",
        "updated_at": "timestamp",
        "object_id": "uuid",
        "id": "uuid",
        "branch_id": "uuid",
        "url": "text",
        "key": "text",
        "user_id": "uuid"
      },
      "type_name": "",
      "table_name": "",
      "base_table": "",
      "partition_keys": [
        "branch_id"
      ],
      "clustering_keys": [
        "id",
        "node_id",
        "object_id"
      ],
      "static_columns": [],
      "global_secondary_indexes": [],
      "local_secondary_indexes": [],
      "table_options": null
    },
    "contribution_requests": {
      "fields": [
        [
          "created_at",
          "timestamp",
          false
        ],
        [
          "description",
          "text",
          false
        ],
        [
          "editor_ids",
          "set<uuid>",
          false
        ],
        [
          "id",
          "uuid",
          false
        ],
        [
          "node_id",
          "uuid",
          false
        ],
        [
          "owner",
          "frozen<profile>",
          false
        ],
        [
          "owner_id",
          "uuid",
          false
        ],
        [
          "root_id",
          "uuid",
          false
        ],
        [
          "status",
          "text",
          false
        ],
        [
          "title",
          "text",
          false
        ],
        [
          "updated_at",
          "timestamp",
          false
        ]
      ],
      "field_names": [
        "description",
        "editor_ids",
        "node_id",
        "owner",
        "owner_id",
        "root_id",
        "id",
        "status",
        "created_at",
        "updated_at",
        "title"
      ],
      "types_by_name": {
        "editor_ids": "set<uuid>",
        "updated_at": "timestamp",
        "description": "text",
        "root_id": "uuid",
        "title": "text",
        "owner": "frozen<profile>",
        "created_at": "timestamp",
        "node_id": "uuid",
        "owner_id": "uuid",
        "id": "uuid",
        "status": "text"
      },
      "type_name": "",
      "table_name": "",
      "base_table": "",
      "partition_keys": [
        "node_id"
      ],
      "clustering_keys": [
        "id"
      ],
      "static_columns": [],
      "global_secondary_indexes": [],
      "local_secondary_indexes": [],
      "table_options": null
    },
    "comments": {
      "fields": [
        [
          "author",
          "frozen<profile>",
          false
        ],
        [
          "author_id",
          "uuid",
          false
        ],
        [
          "content",
          "text",
          false
        ],
        [
          "created_at",
          "timestamp",
          false
        ],
        [
          "id",
          "uuid",
          false
        ],
        [
          "object_id",
          "uuid",
          false
        ],
        [
          "thread_id",
          "uuid",
          false
        ],
        [
          "updated_at",
          "timestamp",
          false
        ],
        [
          "url",
          "text",
          false
        ]
      ],
      "field_names": [
        "url",
        "object_id",
        "thread_id",
        "created_at",
        "author_id",
        "id",
        "updated_at",
        "author",
        "content"
      ],
      "types_by_name": {
        "updated_at": "timestamp",
        "thread_id": "uuid",
        "url": "text",
        "created_at": "timestamp",
        "object_id": "uuid",
        "id": "uuid",
        "author": "frozen<profile>",
        "author_id": "uuid",
        "content": "text"
      },
      "type_name": "",
      "table_name": "",
      "base_table": "",
      "partition_keys": [
        "object_id"
      ],
      "clustering_keys": [
        "id",
        "thread_id"
      ],
      "static_columns": [],
      "global_secondary_indexes": [],
      "local_secondary_indexes": [],
      "table_options": null
    },
    "flows": {
      "fields": [
        [
          "branch_id",
          "uuid",
          false
        ],
        [
          "created_at",
          "timestamp",
          false
        ],
        [
          "id",
          "uuid",
          false
        ],
        [
          "node_id",
          "uuid",
          false
        ],
        [
          "root_id",
          "uuid",
          false
        ],
        [
          "start_index",
          "int",
          false
        ],
        [
          "title",
          "text",
          false
        ],
        [
          "updated_at",
          "timestamp",
          false
        ],
        [
          "vertical_index",
          "double",
          false
        ]
      ],
      "field_names": [
        "title",
        "id",
        "root_id",
        "created_at",
        "branch_id",
        "node_id",
        "start_index",
        "updated_at",
        "vertical_index"
      ],
      "types_by_name": {
        "branch_id": "uuid",
        "start_index": "int",
        "title": "text",
        "node_id": "uuid",
        "root_id": "uuid",
        "id": "uuid",
        "created_at": "timestamp",
        "updated_at": "timestamp",
        "vertical_index": "double"
      },
      "type_name": "",
      "table_name": "",
      "base_table": "",
      "partition_keys": [
        "branch_id"
      ],
      "clustering_keys": [
        "id",
        "node_id",
        "start_index",
        "vertical_index"
      ],
      "static_columns": [],
      "global_secondary_indexes": [],
      "local_secondary_indexes": [
        [
          "flows_branch_id_id_idx",
          "id"
        ]
      ],
      "table_options": null
    },
    "node_counters": {
      "fields": [
        [
          "branch_id",
          "uuid",
          false
        ],
        [
          "descendants_count",
          "counter",
          false
        ],
        [
          "id",
          "uuid",
          false
        ],
        [
          "like_count",
          "counter",
          false
        ]
      ],
      "field_names": [
        "branch_id",
        "descendants_count",
        "id",
        "like_count"
      ],
      "types_by_name": {
        "descendants_count": "counter",
        "id": "uuid",
        "branch_id": "uuid",
        "like_count": "counter"
      },
      "type_name": "",
      "table_name": "",
      "base_table": "",
      "partition_keys": [
        "branch_id"
      ],
      "clustering_keys": [
        "id"
      ],
      "static_columns": [],
      "global_secondary_indexes": [],
      "local_secondary_indexes": [],
      "table_options": null
    },
    "comment_threads": {
      "fields": [
        [
          "author",
          "profile",
          false
        ],
        [
          "author_id",
          "uuid",
          false
        ],
        [
          "created_at",
          "timestamp",
          false
        ],
        [
          "id",
          "uuid",
          false
        ],
        [
          "line_content",
          "text",
          false
        ],
        [
          "line_number",
          "int",
          false
        ],
        [
          "object_id",
          "uuid",
          false
        ],
        [
          "object_node_id",
          "uuid",
          false
        ],
        [
          "object_type",
          "text",
          false
        ],
        [
          "root_id",
          "uuid",
          false
        ],
        [
          "thread_object_id",
          "uuid",
          false
        ],
        [
          "thread_type",
          "text",
          false
        ],
        [
          "title",
          "text",
          false
        ],
        [
          "updated_at",
          "timestamp",
          false
        ]
      ],
      "field_names": [
        "object_id",
        "title",
        "line_content",
        "object_type",
        "root_id",
        "created_at",
        "object_node_id",
        "author",
        "thread_object_id",
        "author_id",
        "id",
        "thread_type",
        "updated_at",
        "line_number"
      ],
      "types_by_name": {
        "author": "profile",
        "root_id": "uuid",
        "thread_object_id": "uuid",
        "thread_type": "text",
        "title": "text",
        "updated_at": "timestamp",
        "line_content": "text",
        "object_id": "uuid",
        "object_node_id": "uuid",
        "object_type": "text",
        "created_at": "timestamp",
        "id": "uuid",
        "line_number": "int",
        "author_id": "uuid"
      },
      "type_name": "",
      "table_name": "",
      "base_table": "",
      "partition_keys": [
        "object_id"
      ],
      "clustering_keys": [
        "id"
      ],
      "static_columns": [],
      "global_secondary_indexes": [],
      "local_secondary_indexes": [],
      "table_options": null
    },
    "archived_descriptions": {
      "fields": [
        [
          "base64",
          "text",
          false
        ],
        [
          "branch_id",
          "uuid",
          false
        ],
        [
          "html",
          "text",
          false
        ],
        [
          "markdown",
          "text",
          false
        ],
        [
          "node_id",
          "uuid",
          false
        ],
        [
          "object_id",
          "uuid",
          false
        ],
        [
          "object_type",
          "text",
          false
        ],
        [
          "root_id",
          "uuid",
          false
        ],
        [
          "short_description",
          "text",
          false
        ],
        [
          "updated_at",
          "timestamp",
          false
        ]
      ],
      "field_names": [
        "base64",
        "html",
        "branch_id",
        "markdown",
        "updated_at",
        "root_id",
        "node_id",
        "object_id",
        "short_description",
        "object_type"
      ],
      "types_by_name": {
        "object_type": "text",
        "html": "text",
        "short_description": "text",
        "branch_id": "uuid",
        "root_id": "uuid",
        "markdown": "text",
        "updated_at": "timestamp",
        "node_id": "uuid",
        "base64": "text",
        "object_id": "uuid"
      },
      "type_name": "",
      "table_name": "",
      "base_table": "",
      "partition_keys": [
        "branch_id"
      ],
      "clustering_keys": [
        "object_id"
      ],
      "static_columns": [],
      "global_secondary_indexes": [],
      "local_secondary_indexes": [],
      "table_options": null
    },
    "recoveries": {
      "fields": [
        [
          "branch_id",
          "uuid",
          false
        ],
        [
          "data",
          "text",
          false
        ],
        [
          "id",
          "uuid",
          false
        ],
        [
          "object_type",
          "tinyint",
          false
        ],
        [
          "step",
          "tinyint",
          false
        ],
        [
          "updated_at",
          "timestamp",
          false
        ]
      ],
      "field_names": [
        "updated_at",
        "branch_id",
        "object_type",
        "id",
        "step",
        "data"
      ],
      "types_by_name": {
        "data": "text",
        "updated_at": "timestamp",
        "id": "uuid",
        "step": "tinyint",
        "branch_id": "uuid",
        "object_type": "tinyint"
      },
      "type_name": "",
      "table_name": "",
      "base_table": "",
      "partition_keys": [
        "branch_id"
      ],
      "clustering_keys": [
        "id",
        "object_type"
      ],
      "static_columns": [],
      "global_secondary_indexes": [
        [
          "recoveries_updated_at_idx",
          "updated_at"
        ]
      ],
      "local_secondary_indexes": [],
      "table_options": null
    },
    "users": {
      "fields": [
        [
          "address",
          "address",
          false
        ],
        [
          "bio",
          "text",
          false
        ],
        [
          "created_at",
          "timestamp",
          false
        ],
        [
          "email",
          "text",
          false
        ],
        [
          "first_name",
          "text",
          false
        ],
        [
          "id",
          "uuid",
          false
        ],
        [
          "is_blocked",
          "boolean",
          false
        ],
        [
          "is_confirmed",
          "boolean",
          false
        ],
        [
          "last_name",
          "text",
          false
        ],
        [
          "password",
          "text",
          false
        ],
        [
          "profile_image_filename",
          "text",
          false
        ],
        [
          "profile_image_url",
          "text",
          false
        ],
        [
          "updated_at",
          "timestamp",
          false
        ],
        [
          "username",
          "text",
          false
        ]
      ],
      "field_names": [
        "last_name",
        "first_name",
        "profile_image_filename",
        "profile_image_url",
        "is_blocked",
        "username",
        "id",
        "address",
        "email",
        "bio",
        "password",
        "updated_at",
        "created_at",
        "is_confirmed"
      ],
      "types_by_name": {
        "last_name": "text",
        "profile_image_filename": "text",
        "username": "text",
        "password": "text",
        "profile_image_url": "text",
        "id": "uuid",
        "is_blocked": "boolean",
        "first_name": "text",
        "bio": "text",
        "address": "address",
        "email": "text",
        "created_at": "timestamp",
        "is_confirmed": "boolean",
        "updated_at": "timestamp"
      },
      "type_name": "",
      "table_name": "",
      "base_table": "",
      "partition_keys": [
        "id"
      ],
      "clustering_keys": [],
      "static_columns": [],
      "global_secondary_indexes": [
        [
          "users_email_idx",
          "email"
        ],
        [
          "users_username_idx",
          "username"
        ]
      ],
      "local_secondary_indexes": [],
      "table_options": null
    },
    "archived_flow_steps": {
      "fields": [
        [
          "branch_id",
          "uuid",
          false
        ],
        [
          "created_at",
          "timestamp",
          false
        ],
        [
          "flow_id",
          "uuid",
          false
        ],
        [
          "id",
          "uuid",
          false
        ],
        [
          "input_ids_by_node_id",
          "frozen<map<uuid, frozen<list<uuid>>>>",
          false
        ],
        [
          "node_id",
          "uuid",
          false
        ],
        [
          "node_ids",
          "list<uuid>",
          false
        ],
        [
          "output_ids_by_node_id",
          "frozen<map<uuid, frozen<list<uuid>>>>",
          false
        ],
        [
          "root_id",
          "uuid",
          false
        ],
        [
          "step_index",
          "decimal",
          false
        ],
        [
          "updated_at",
          "timestamp",
          false
        ]
      ],
      "field_names": [
        "branch_id",
        "node_id",
        "output_ids_by_node_id",
        "root_id",
        "created_at",
        "updated_at",
        "step_index",
        "flow_id",
        "node_ids",
        "input_ids_by_node_id",
        "id"
      ],
      "types_by_name": {
        "output_ids_by_node_id": "frozen<map<uuid, frozen<list<uuid>>>>",
        "step_index": "decimal",
        "updated_at": "timestamp",
        "node_id": "uuid",
        "input_ids_by_node_id": "frozen<map<uuid, frozen<list<uuid>>>>",
        "created_at": "timestamp",
        "flow_id": "uuid",
        "root_id": "uuid",
        "node_ids": "list<uuid>",
        "branch_id": "uuid",
        "id": "uuid"
      },
      "type_name": "",
      "table_name": "",
      "base_table": "",
      "partition_keys": [
        "branch_id"
      ],
      "clustering_keys": [
        "flow_id",
        "id",
        "node_id",
        "step_index"
      ],
      "static_columns": [],
      "global_secondary_indexes": [],
      "local_secondary_indexes": [],
      "table_options": null
    },
    "archived_nodes": {
      "fields": [
        [
          "ancestor_ids",
          "set<uuid>",
          false
        ],
        [
          "branch_id",
          "uuid",
          false
        ],
        [
          "cover_image_filename",
          "text",
          false
        ],
        [
          "cover_image_url",
          "text",
          false
        ],
        [
          "created_at",
          "timestamp",
          false
        ],
        [
          "editor_ids",
          "set<uuid>",
          false
        ],
        [
          "id",
          "uuid",
          false
        ],
        [
          "is_public",
          "boolean",
          false
        ],
        [
          "is_root",
          "boolean",
          false
        ],
        [
          "order_index",
          "double",
          false
        ],
        [
          "owner",
          "frozen<profile>",
          false
        ],
        [
          "owner_id",
          "uuid",
          false
        ],
        [
          "parent_id",
          "uuid",
          false
        ],
        [
          "root_id",
          "uuid",
          false
        ],
        [
          "title",
          "text",
          false
        ],
        [
          "updated_at",
          "timestamp",
          false
        ],
        [
          "viewer_ids",
          "set<uuid>",
          false
        ]
      ],
      "field_names": [
        "is_public",
        "parent_id",
        "editor_ids",
        "owner_id",
        "created_at",
        "ancestor_ids",
        "cover_image_filename",
        "root_id",
        "title",
        "is_root",
        "owner",
        "id",
        "updated_at",
        "cover_image_url",
        "viewer_ids",
        "branch_id",
        "order_index"
      ],
      "types_by_name": {
        "branch_id": "uuid",
        "id": "uuid",
        "cover_image_filename": "text",
        "is_root": "boolean",
        "order_index": "double",
        "editor_ids": "set<uuid>",
        "owner": "frozen<profile>",
        "created_at": "timestamp",
        "owner_id": "uuid",
        "parent_id": "uuid",
        "ancestor_ids": "set<uuid>",
        "title": "text",
        "is_public": "boolean",
        "cover_image_url": "text",
        "root_id": "uuid",
        "viewer_ids": "set<uuid>",
        "updated_at": "timestamp"
      },
      "type_name": "",
      "table_name": "",
      "base_table": "",
      "partition_keys": [
        "branch_id"
      ],
      "clustering_keys": [
        "id"
      ],
      "static_columns": [],
      "global_secondary_indexes": [],
      "local_secondary_indexes": [],
      "table_options": null
    },
    "likes": {
      "fields": [
        [
          "branch_id",
          "uuid",
          false
        ],
        [
          "created_at",
          "timestamp",
          false
        ],
        [
          "object_id",
          "uuid",
          false
        ],
        [
          "object_type",
          "text",
          false
        ],
        [
          "updated_at",
          "timestamp",
          false
        ],
        [
          "user_id",
          "uuid",
          false
        ],
        [
          "username",
          "text",
          false
        ]
      ],
      "field_names": [
        "object_type",
        "branch_id",
        "created_at",
        "object_id",
        "updated_at",
        "user_id",
        "username"
      ],
      "types_by_name": {
        "object_type": "text",
        "updated_at": "timestamp",
        "object_id": "uuid",
        "created_at": "timestamp",
        "branch_id": "uuid",
        "user_id": "uuid",
        "username": "text"
      },
      "type_name": "",
      "table_name": "",
      "base_table": "",
      "partition_keys": [
        "object_id"
      ],
      "clustering_keys": [
        "branch_id",
        "user_id"
      ],
      "static_columns": [],
      "global_secondary_indexes": [],
      "local_secondary_indexes": [],
      "table_options": null
    },
    "user_counters": {
      "fields": [
        [
          "id",
          "uuid",
          false
        ],
        [
          "resend_token_count",
          "counter",
          false
        ]
      ],
      "field_names": [
        "id",
        "resend_token_count"
      ],
      "types_by_name": {
        "id": "uuid",
        "resend_token_count": "counter"
      },
      "type_name": "",
      "table_name": "",
      "base_table": "",
      "partition_keys": [
        "id"
      ],
      "clustering_keys": [],
      "static_columns": [],
      "global_secondary_indexes": [],
      "local_secondary_indexes": [],
      "table_options": null
    },
    "workflows": {
      "fields": [
        [
          "branch_id",
          "uuid",
          false
        ],
        [
          "created_at",
          "timestamp",
          false
        ],
        [
          "initial_input_ids",
          "list<uuid>",
          false
        ],
        [
          "node_id",
          "uuid",
          false
        ],
        [
          "root_id",
          "uuid",
          false
        ],
        [
          "title",
          "text",
          false
        ],
        [
          "updated_at",
          "timestamp",
          false
        ]
      ],
      "field_names": [
        "updated_at",
        "node_id",
        "initial_input_ids",
        "created_at",
        "branch_id",
        "root_id",
        "title"
      ],
      "types_by_name": {
        "root_id": "uuid",
        "created_at": "timestamp",
        "updated_at": "timestamp",
        "initial_input_ids": "list<uuid>",
        "title": "text",
        "branch_id": "uuid",
        "node_id": "uuid"
      },
      "type_name": "",
      "table_name": "",
      "base_table": "",
      "partition_keys": [
        "branch_id"
      ],
      "clustering_keys": [
        "node_id"
      ],
      "static_columns": [],
      "global_secondary_indexes": [],
      "local_secondary_indexes": [],
      "table_options": null
    },
    "tokens": {
      "fields": [
        [
          "created_at",
          "timestamp",
          false
        ],
        [
          "email",
          "text",
          false
        ],
        [
          "expires_at",
          "timestamp",
          false
        ],
        [
          "id",
          "text",
          false
        ],
        [
          "node_pk",
          "frozen<tuple<uuid, uuid>>",
          false
        ],
        [
          "token_type",
          "text",
          false
        ],
        [
          "username",
          "text",
          false
        ]
      ],
      "field_names": [
        "token_type",
        "node_pk",
        "email",
        "created_at",
        "id",
        "expires_at",
        "username"
      ],
      "types_by_name": {
        "id": "text",
        "token_type": "text",
        "username": "text",
        "email": "text",
        "created_at": "timestamp",
        "expires_at": "timestamp",
        "node_pk": "frozen<tuple<uuid, uuid>>"
      },
      "type_name": "",
      "table_name": "",
      "base_table": "",
      "partition_keys": [
        "id"
      ],
      "clustering_keys": [],
      "static_columns": [],
      "global_secondary_indexes": [],
      "local_secondary_indexes": [],
      "table_options": null
    },
    "node_descendants": {
      "fields": [
        [
          "branch_id",
          "uuid",
          false
        ],
        [
          "id",
          "uuid",
          false
        ],
        [
          "node_id",
          "uuid",
          false
        ],
        [
          "order_index",
          "double",
          false
        ],
        [
          "parent_id",
          "uuid",
          false
        ],
        [
          "root_id",
          "uuid",
          false
        ],
        [
          "title",
          "text",
          false
        ]
      ],
      "field_names": [
        "order_index",
        "id",
        "root_id",
        "title",
        "node_id",
        "parent_id",
        "branch_id"
      ],
      "types_by_name": {
        "root_id": "uuid",
        "node_id": "uuid",
        "id": "uuid",
        "title": "text",
        "parent_id": "uuid",
        "branch_id": "uuid",
        "order_index": "double"
      },
      "type_name": "",
      "table_name": "",
      "base_table": "",
      "partition_keys": [
        "root_id"
      ],
      "clustering_keys": [
        "branch_id",
        "id",
        "node_id",
        "order_index"
      ],
      "static_columns": [],
      "global_secondary_indexes": [],
      "local_secondary_indexes": [],
      "table_options": null
    },
    "flow_steps": {
      "fields": [
        [
          "branch_id",
          "uuid",
          false
        ],
        [
          "created_at",
          "timestamp",
          false
        ],
        [
          "flow_id",
          "uuid",
          false
        ],
        [
          "id",
          "uuid",
          false
        ],
        [
          "input_ids_by_node_id",
          "frozen<map<uuid, frozen<list<uuid>>>>",
          false
        ],
        [
          "node_id",
          "uuid",
          false
        ],
        [
          "node_ids",
          "list<uuid>",
          false
        ],
        [
          "output_ids_by_node_id",
          "frozen<map<uuid, frozen<list<uuid>>>>",
          false
        ],
        [
          "root_id",
          "uuid",
          false
        ],
        [
          "step_index",
          "decimal",
          false
        ],
        [
          "updated_at",
          "timestamp",
          false
        ]
      ],
      "field_names": [
        "node_id",
        "created_at",
        "output_ids_by_node_id",
        "step_index",
        "updated_at",
        "node_ids",
        "input_ids_by_node_id",
        "flow_id",
        "branch_id",
        "id",
        "root_id"
      ],
      "types_by_name": {
        "created_at": "timestamp",
        "branch_id": "uuid",
        "node_id": "uuid",
        "output_ids_by_node_id": "frozen<map<uuid, frozen<list<uuid>>>>",
        "root_id": "uuid",
        "node_ids": "list<uuid>",
        "input_ids_by_node_id": "frozen<map<uuid, frozen<list<uuid>>>>",
        "id": "uuid",
        "step_index": "decimal",
        "updated_at": "timestamp",
        "flow_id": "uuid"
      },
      "type_name": "",
      "table_name": "",
      "base_table": "",
      "partition_keys": [
        "branch_id"
      ],
      "clustering_keys": [
        "flow_id",
        "id",
        "node_id",
        "step_index"
      ],
      "static_columns": [],
      "global_secondary_indexes": [],
      "local_secondary_indexes": [
        [
          "flow_steps_branch_id_id_idx",
          "id"
        ]
      ],
      "table_options": null
    },
    "description": {
      "fields": [
        [
          "base64",
          "text",
          false
        ],
        [
          "branch_id",
          "uuid",
          false
        ],
        [
          "html",
          "text",
          false
        ],
        [
          "markdown",
          "text",
          false
        ],
        [
          "node_id",
          "uuid",
          false
        ],
        [
          "object_id",
          "uuid",
          false
        ],
        [
          "object_type",
          "text",
          false
        ],
        [
          "root_id",
          "uuid",
          false
        ],
        [
          "short_description",
          "text",
          false
        ],
        [
          "updated_at",
          "timestamp",
          false
        ]
      ],
      "field_names": [
        "branch_id",
        "html",
        "markdown",
        "object_type",
        "short_description",
        "base64",
        "updated_at",
        "node_id",
        "root_id",
        "object_id"
      ],
      "types_by_name": {
        "updated_at": "timestamp",
        "markdown": "text",
        "branch_id": "uuid",
        "object_id": "uuid",
        "short_description": "text",
        "html": "text",
        "node_id": "uuid",
        "root_id": "uuid",
        "base64": "text",
        "object_type": "text"
      },
      "type_name": "",
      "table_name": "",
      "base_table": "",
      "partition_keys": [
        "branch_id"
      ],
      "clustering_keys": [
        "object_id"
      ],
      "static_columns": [],
      "global_secondary_indexes": [],
      "local_secondary_indexes": [],
      "table_options": null
    },
    "archived_workflows": {
      "fields": [
        [
          "branch_id",
          "uuid",
          false
        ],
        [
          "created_at",
          "timestamp",
          false
        ],
        [
          "initial_input_ids",
          "list<uuid>",
          false
        ],
        [
          "node_id",
          "uuid",
          false
        ],
        [
          "root_id",
          "uuid",
          false
        ],
        [
          "title",
          "text",
          false
        ],
        [
          "updated_at",
          "timestamp",
          false
        ]
      ],
      "field_names": [
        "branch_id",
        "updated_at",
        "created_at",
        "root_id",
        "title",
        "initial_input_ids",
        "node_id"
      ],
      "types_by_name": {
        "branch_id": "uuid",
        "root_id": "uuid",
        "node_id": "uuid",
        "created_at": "timestamp",
        "initial_input_ids": "list<uuid>",
        "title": "text",
        "updated_at": "timestamp"
      },
      "type_name": "",
      "table_name": "",
      "base_table": "",
      "partition_keys": [
        "branch_id"
      ],
      "clustering_keys": [
        "node_id"
      ],
      "static_columns": [],
      "global_secondary_indexes": [],
      "local_secondary_indexes": [],
      "table_options": null
    }
  },
  "udts": {
    "profile": {
      "fields": [
        [
          "id",
          "uuid",
          false
        ],
        [
          "profile_type",
          "text",
          false
        ],
        [
          "name",
          "text",
          false
        ],
        [
          "username",
          "text",
          false
        ],
        [
          "profile_image_url",
          "text",
          false
        ]
      ],
      "field_names": [
        "profile_image_url",
        "name",
        "profile_type",
        "id",
        "username"
      ],
      "types_by_name": {
        "name": "text",
        "profile_type": "text",
        "username": "text",
        "id": "uuid",
        "profile_image_url": "text"
      },
      "type_name": "",
      "table_name": "",
      "base_table": "",
      "partition_keys": [],
      "clustering_keys": [],
      "static_columns": [],
      "global_secondary_indexes": [],
      "local_secondary_indexes": [],
      "table_options": null
    },
    "textchange": {
      "fields": [
        [
          "old",
          "text",
          false
        ],
        [
          "new",
          "text",
          false
        ]
      ],
      "field_names": [
        "old",
        "new"
      ],
      "types_by_name": {
        "new": "text",
        "old": "text"
      },
      "type_name": "",
      "table_name": "",
      "base_table": "",
      "partition_keys": [],
      "clustering_keys": [],
      "static_columns": [],
      "global_secondary_indexes": [],
      "local_secondary_indexes": [],
      "table_options": null
    },
    "address": {
      "fields": [
        [
          "street",
          "text",
          false
        ],
        [
          "city",
          "text",
          false
        ],
        [
          "state",
          "text",
          false
        ],
        [
          "zip",
          "text",
          false
        ],
        [
          "country",
          "text",
          false
        ]
      ],
      "field_names": [
        "street",
        "zip",
        "country",
        "state",
        "city"
      ],
      "types_by_name": {
        "street": "text",
        "zip": "text",
        "city": "text",
        "country": "text",
        "state": "text"
      },
      "type_name": "",
      "table_name": "",
      "base_table": "",
      "partition_keys": [],
      "clustering_keys": [],
      "static_columns": [],
      "global_secondary_indexes": [],
      "local_secondary_indexes": [],
      "table_options": null
    },
    "branchreorderdata": {
      "fields": [
        [
          "id",
          "uuid",
          false
        ],
        [
          "new_parent_id",
          "uuid",
          false
        ],
        [
          "new_upper_sibling_id",
          "uuid",
          false
        ],
        [
          "new_lower_sibling_id",
          "uuid",
          false
        ],
        [
          "old_parent_id",
          "uuid",
          false
        ],
        [
          "old_order_index",
          "double",
          false
        ]
      ],
      "field_names": [
        "id",
        "old_order_index",
        "new_parent_id",
        "new_upper_sibling_id",
        "new_lower_sibling_id",
        "old_parent_id"
      ],
      "types_by_name": {
        "new_parent_id": "uuid",
        "old_order_index": "double",
        "id": "uuid",
        "new_upper_sibling_id": "uuid",
        "new_lower_sibling_id": "uuid",
        "old_parent_id": "uuid"
      },
      "type_name": "",
      "table_name": "",
      "base_table": "",
      "partition_keys": [],
      "clustering_keys": [],
      "static_columns": [],
      "global_secondary_indexes": [],
      "local_secondary_indexes": [],
      "table_options": null
    },
    "conflict": {
      "fields": [
        [
          "deleted_ancestors",
          "frozen<set<uuid>>",
          false
        ],
        [
          "deleted_edited_nodes",
          "frozen<set<uuid>>",
          false
        ],
        [
          "deleted_edited_flows",
          "frozen<set<uuid>>",
          false
        ],
        [
          "deleted_edited_flow_steps",
          "frozen<set<uuid>>",
          false
        ],
        [
          "deleted_edited_ios",
          "frozen<set<uuid>>",
          false
        ],
        [
          "conflicting_flow_steps",
          "frozen<set<uuid>>",
          false
        ]
      ],
      "field_names": [
        "deleted_edited_flows",
        "deleted_ancestors",
        "deleted_edited_nodes",
        "deleted_edited_flow_steps",
        "deleted_edited_ios",
        "conflicting_flow_steps"
      ],
      "types_by_name": {
        "deleted_edited_nodes": "frozen<set<uuid>>",
        "conflicting_flow_steps": "frozen<set<uuid>>",
        "deleted_edited_ios": "frozen<set<uuid>>",
        "deleted_ancestors": "frozen<set<uuid>>",
        "deleted_edited_flow_steps": "frozen<set<uuid>>",
        "deleted_edited_flows": "frozen<set<uuid>>"
      },
      "type_name": "",
      "table_name": "",
      "base_table": "",
      "partition_keys": [],
      "clustering_keys": [],
      "static_columns": [],
      "global_secondary_indexes": [],
      "local_secondary_indexes": [],
      "table_options": null
    }
  },
  "materialized_views": {
    "archived_flows_branch_id_id_idx_index": {
      "fields": [
        [
          "branch_id",
          "uuid",
          false
        ],
        [
          "id",
          "uuid",
          false
        ],
        [
          "node_id",
          "uuid",
          false
        ],
        [
          "start_index",
          "int",
          false
        ],
        [
          "vertical_index",
          "double",
          false
        ]
      ],
      "field_names": [
        "start_index",
        "vertical_index",
        "node_id",
        "branch_id",
        "id"
      ],
      "types_by_name": {
        "node_id": "uuid",
        "vertical_index": "double",
        "start_index": "int",
        "branch_id": "uuid",
        "id": "uuid"
      },
      "type_name": "",
      "table_name": "",
      "base_table": "",
      "partition_keys": [
        "branch_id"
      ],
      "clustering_keys": [
        "id",
        "node_id",
        "start_index",
        "vertical_index"
      ],
      "static_columns": [],
      "global_secondary_indexes": [],
      "local_secondary_indexes": [],
      "table_options": null
    },
    "users_username_idx_index": {
      "fields": [
        [
          "id",
          "uuid",
          false
        ],
        [
          "idx_token",
          "bigint",
          false
        ],
        [
          "username",
          "text",
          false
        ]
      ],
      "field_names": [
        "id",
        "idx_token",
        "username"
      ],
      "types_by_name": {
        "idx_token": "bigint",
        "username": "text",
        "id": "uuid"
      },
      "type_name": "",
      "table_name": "",
      "base_table": "",
      "partition_keys": [
        "username"
      ],
      "clustering_keys": [
        "id",
        "idx_token"
      ],
      "static_columns": [],
      "global_secondary_indexes": [],
      "local_secondary_indexes": [],
      "table_options": null
    },
    "flow_steps_branch_id_id_idx_index": {
      "fields": [
        [
          "branch_id",
          "uuid",
          false
        ],
        [
          "flow_id",
          "uuid",
          false
        ],
        [
          "id",
          "uuid",
          false
        ],
        [
          "node_id",
          "uuid",
          false
        ],
        [
          "step_index",
          "decimal",
          false
        ]
      ],
      "field_names": [
        "branch_id",
        "node_id",
        "id",
        "step_index",
        "flow_id"
      ],
      "types_by_name": {
        "node_id": "uuid",
        "id": "uuid",
        "branch_id": "uuid",
        "step_index": "decimal",
        "flow_id": "uuid"
      },
      "type_name": "",
      "table_name": "",
      "base_table": "",
      "partition_keys": [
        "branch_id"
      ],
      "clustering_keys": [
        "flow_id",
        "id",
        "node_id",
        "step_index"
      ],
      "static_columns": [],
      "global_secondary_indexes": [],
      "local_secondary_indexes": [],
      "table_options": null
    },
    "flows_branch_id_id_idx_index": {
      "fields": [
        [
          "branch_id",
          "uuid",
          false
        ],
        [
          "id",
          "uuid",
          false
        ],
        [
          "node_id",
          "uuid",
          false
        ],
        [
          "start_index",
          "int",
          false
        ],
        [
          "vertical_index",
          "double",
          false
        ]
      ],
      "field_names": [
        "branch_id",
        "id",
        "node_id",
        "start_index",
        "vertical_index"
      ],
      "types_by_name": {
        "start_index": "int",
        "id": "uuid",
        "node_id": "uuid",
        "vertical_index": "double",
        "branch_id": "uuid"
      },
      "type_name": "",
      "table_name": "",
      "base_table": "",
      "partition_keys": [
        "branch_id"
      ],
      "clustering_keys": [
        "id",
        "node_id",
        "start_index",
        "vertical_index"
      ],
      "static_columns": [],
      "global_secondary_indexes": [],
      "local_secondary_indexes": [],
      "table_options": null
    },
    "nodes_by_owner": {
      "fields": [
        [
          "branch_id",
          "uuid",
          false
        ],
        [
          "id",
          "uuid",
          false
        ],
        [
          "owner_id",
          "uuid",
          false
        ],
        [
          "root_id",
          "uuid",
          false
        ]
      ],
      "field_names": [
        "owner_id",
        "id",
        "root_id",
        "branch_id"
      ],
      "types_by_name": {
        "branch_id": "uuid",
        "owner_id": "uuid",
        "root_id": "uuid",
        "id": "uuid"
      },
      "type_name": "",
      "table_name": "",
      "base_table": "",
      "partition_keys": [
        "owner_id"
      ],
      "clustering_keys": [
        "branch_id",
        "id"
      ],
      "static_columns": [],
      "global_secondary_indexes": [],
      "local_secondary_indexes": [],
      "table_options": null
    },
    "input_outputs_branch_id_node_id_idx_index": {
      "fields": [
        [
          "branch_id",
          "uuid",
          false
        ],
        [
          "id",
          "uuid",
          false
        ],
        [
          "node_id",
          "uuid",
          false
        ],
        [
          "root_id",
          "uuid",
          false
        ]
      ],
      "field_names": [
        "id",
        "root_id",
        "branch_id",
        "node_id"
      ],
      "types_by_name": {
        "node_id": "uuid",
        "root_id": "uuid",
        "branch_id": "uuid",
        "id": "uuid"
      },
      "type_name": "",
      "table_name": "",
      "base_table": "",
      "partition_keys": [
        "branch_id"
      ],
      "clustering_keys": [
        "id",
        "node_id",
        "root_id"
      ],
      "static_columns": [],
      "global_secondary_indexes": [],
      "local_secondary_indexes": [],
      "table_options": null
    },
    "users_email_idx_index": {
      "fields": [
        [
          "email",
          "text",
          false
        ],
        [
          "id",
          "uuid",
          false
        ],
        [
          "idx_token",
          "bigint",
          false
        ]
      ],
      "field_names": [
        "email",
        "id",
        "idx_token"
      ],
      "types_by_name": {
        "idx_token": "bigint",
        "id": "uuid",
        "email": "text"
      },
      "type_name": "",
      "table_name": "",
      "base_table": "",
      "partition_keys": [
        "email"
      ],
      "clustering_keys": [
        "id",
        "idx_token"
      ],
      "static_columns": [],
      "global_secondary_indexes": [],
      "local_secondary_indexes": [],
      "table_options": null
    },
    "recoveries_updated_at_idx_index": {
      "fields": [
        [
          "branch_id",
          "uuid",
          false
        ],
        [
          "id",
          "uuid",
          false
        ],
        [
          "idx_token",
          "bigint",
          false
        ],
        [
          "object_type",
          "tinyint",
          false
        ],
        [
          "updated_at",
          "timestamp",
          false
        ]
      ],
      "field_names": [
        "branch_id",
        "updated_at",
        "id",
        "idx_token",
        "object_type"
      ],
      "types_by_name": {
        "object_type": "tinyint",
        "updated_at": "timestamp",
        "id": "uuid",
        "idx_token": "bigint",
        "branch_id": "uuid"
      },
      "type_name": "",
      "table_name": "",
      "base_table": "",
      "partition_keys": [
        "updated_at"
      ],
      "clustering_keys": [
        "branch_id",
        "id",
        "idx_token",
        "object_type"
      ],
      "static_columns": [],
      "global_secondary_indexes": [],
      "local_secondary_indexes": [],
      "table_options": null
    },
    "input_outputs_branch_id_main_id_idx_index": {
      "fields": [
        [
          "branch_id",
          "uuid",
          false
        ],
        [
          "id",
          "uuid",
          false
        ],
        [
          "main_id",
          "uuid",
          false
        ],
        [
          "root_id",
          "uuid",
          false
        ]
      ],
      "field_names": [
        "main_id",
        "id",
        "branch_id",
        "root_id"
      ],
      "types_by_name": {
        "main_id": "uuid",
        "branch_id": "uuid",
        "root_id": "uuid",
        "id": "uuid"
      },
      "type_name": "",
      "table_name": "",
      "base_table": "",
      "partition_keys": [
        "branch_id"
      ],
      "clustering_keys": [
        "id",
        "main_id",
        "root_id"
      ],
      "static_columns": [],
      "global_secondary_indexes": [],
      "local_secondary_indexes": [],
      "table_options": null
    },
    "likes_by_user_id": {
      "fields": [
        [
          "branch_id",
          "uuid",
          false
        ],
        [
          "object_id",
          "uuid",
          false
        ],
        [
          "user_id",
          "uuid",
          false
        ]
      ],
      "field_names": [
        "user_id",
        "object_id",
        "branch_id"
      ],
      "types_by_name": {
        "user_id": "uuid",
        "object_id": "uuid",
        "branch_id": "uuid"
      },
      "type_name": "",
      "table_name": "",
      "base_table": "",
      "partition_keys": [
        "user_id"
      ],
      "clustering_keys": [
        "branch_id",
        "object_id"
      ],
      "static_columns": [],
      "global_secondary_indexes": [],
      "local_secondary_indexes": [],
      "table_options": null
    }
  },
  "keyspace_name": "nodecosmos"
}