{
  "tables": {
    "users": {
      "fields": {
        "address": "address",
        "confirmed": "boolean",
        "created_at": "timestamp",
        "id": "uuid",
        "last_name": "text",
        "first_name": "text",
        "updated_at": "timestamp",
        "liked_object_ids": "set<uuid>",
        "password": "text",
        "username": "text",
        "email": "text"
      },
      "type_name": "",
      "table_name": "",
      "base_table": "",
      "partition_keys": [
        "id"
      ],
      "clustering_keys": [],
      "secondary_indexes": [
        "users_email_idx",
        "users_username_idx"
      ]
    }
  },
  "udts": {
    "property": {
      "fields": {
        "data_type": "text",
        "title": "text",
        "value": "text"
      },
      "type_name": "",
      "table_name": "",
      "base_table": "",
      "partition_keys": [],
      "clustering_keys": [],
      "secondary_indexes": []
    },
    "owner": {
      "fields": {
        "id": "uuid",
        "username": "text"
      },
      "type_name": "",
      "table_name": "",
      "base_table": "",
      "partition_keys": [],
      "clustering_keys": [],
      "secondary_indexes": []
    },
    "address": {
      "fields": {
        "street": "text",
        "zip": "text",
        "state": "text",
        "city": "text",
        "country": "text"
      },
      "type_name": "",
      "table_name": "",
      "base_table": "",
      "partition_keys": [],
      "clustering_keys": [],
      "secondary_indexes": []
    },
    "creator": {
      "fields": {
        "id": "uuid",
        "username": "text"
      },
      "type_name": "",
      "table_name": "",
      "base_table": "",
      "partition_keys": [],
      "clustering_keys": [],
      "secondary_indexes": []
    }
  },
  "materialized_views": {
    "users_username_idx_index": {
      "fields": {
        "username": "text",
        "id": "uuid",
        "idx_token": "bigint"
      },
      "type_name": "",
      "table_name": "",
      "base_table": "",
      "partition_keys": [
        "username"
      ],
      "clustering_keys": [
        "id",
        "idx_token"
      ],
      "secondary_indexes": []
    },
    "users_email_idx_index": {
      "fields": {
        "id": "uuid",
        "idx_token": "bigint",
        "email": "text"
      },
      "type_name": "",
      "table_name": "",
      "base_table": "",
      "partition_keys": [
        "email"
      ],
      "clustering_keys": [
        "id",
        "idx_token"
      ],
      "secondary_indexes": []
    }
  },
  "keyspace_name": "nodecosmos"
}