{
  "tables": {
    "attachments": {
      "fields": {
        "url": "text",
        "id": "uuid",
        "created_at": "timestamp",
        "object_id": "uuid",
        "user_id": "uuid",
        "node_id": "uuid",
        "updated_at": "timestamp",
        "key": "text"
      },
      "type_name": "",
      "table_name": "",
      "base_table": "",
      "partition_keys": [
        "node_id"
      ],
      "clustering_keys": [
        "id",
        "object_id"
      ],
      "global_secondary_indexes": null,
      "local_secondary_indexes": null,
      "table_options": null
    },
    "nodes": {
      "fields": {
        "creator": "creator",
        "description": "text",
        "owner_type": "text",
        "title": "text",
        "editor_ids": "set<uuid>",
        "ancestor_ids": "set<uuid>",
        "order_index": "double",
        "id": "uuid",
        "is_root": "boolean",
        "cover_image_url": "text",
        "cover_image_filename": "text",
        "is_public": "boolean",
        "root_id": "uuid",
        "likes_count": "bigint",
        "created_at": "timestamp",
        "updated_at": "timestamp",
        "description_base64": "text",
        "creator_id": "uuid",
        "description_markdown": "text",
        "owner": "owner",
        "owner_id": "uuid",
        "parent_id": "uuid",
        "short_description": "text"
      },
      "type_name": "",
      "table_name": "",
      "base_table": "",
      "partition_keys": [
        "id"
      ],
      "clustering_keys": [],
      "global_secondary_indexes": null,
      "local_secondary_indexes": null,
      "table_options": null
    },
    "workflows": {
      "fields": {
        "node_id": "uuid",
        "flow_ids": "list<uuid>",
        "description_markdown": "text",
        "updated_at": "timestamp",
        "created_at": "timestamp",
        "root_node_id": "uuid",
        "description": "text",
        "title": "text",
        "initial_input_ids": "list<uuid>",
        "id": "uuid"
      },
      "type_name": "",
      "table_name": "",
      "base_table": "",
      "partition_keys": [
        "node_id"
      ],
      "clustering_keys": [
        "id"
      ],
      "global_secondary_indexes": null,
      "local_secondary_indexes": null,
      "table_options": null
    },
    "likes": {
      "fields": {
        "username": "text",
        "user_id": "uuid",
        "object_type": "text",
        "created_at": "timestamp",
        "object_id": "uuid",
        "updated_at": "timestamp"
      },
      "type_name": "",
      "table_name": "",
      "base_table": "",
      "partition_keys": [
        "object_id"
      ],
      "clustering_keys": [
        "user_id"
      ],
      "global_secondary_indexes": null,
      "local_secondary_indexes": null,
      "table_options": null
    },
    "flow_steps": {
      "fields": {
        "input_ids_by_node_id": "frozen<map<uuid, frozen<list<uuid>>>>",
        "node_ids": "list<uuid>",
        "updated_at": "timestamp",
        "workflow_id": "uuid",
        "node_id": "uuid",
        "output_ids_by_node_id": "frozen<map<uuid, frozen<list<uuid>>>>",
        "workflow_index": "int",
        "flow_id": "uuid",
        "description": "text",
        "created_at": "timestamp",
        "description_markdown": "text",
        "id": "uuid"
      },
      "type_name": "",
      "table_name": "",
      "base_table": "",
      "partition_keys": [
        "node_id"
      ],
      "clustering_keys": [
        "id",
        "workflow_id",
        "workflow_index"
      ],
      "global_secondary_indexes": null,
      "local_secondary_indexes": null,
      "table_options": null
    },
    "contribution_requests": {
      "fields": {
        "created_at": "timestamp",
        "description": "text",
        "updated_at": "timestamp",
        "description_markdown": "text",
        "editor_ids": "list<uuid>",
        "node_id": "uuid",
        "owner": "owner",
        "id": "uuid",
        "owner_id": "uuid",
        "commit_ids": "list<uuid>",
        "status": "text",
        "title": "text"
      },
      "type_name": "",
      "table_name": "",
      "base_table": "",
      "partition_keys": [
        "node_id"
      ],
      "clustering_keys": [
        "id"
      ],
      "global_secondary_indexes": null,
      "local_secondary_indexes": null,
      "table_options": null
    },
    "likes_count": {
      "fields": {
        "object_id": "uuid",
        "count": "counter"
      },
      "type_name": "",
      "table_name": "",
      "base_table": "",
      "partition_keys": [
        "object_id"
      ],
      "clustering_keys": [],
      "global_secondary_indexes": null,
      "local_secondary_indexes": null,
      "table_options": null
    },
    "users": {
      "fields": {
        "created_at": "timestamp",
        "id": "uuid",
        "address": "address",
        "email": "text",
        "is_blocked": "boolean",
        "is_confirmed": "boolean",
        "first_name": "text",
        "password": "text",
        "updated_at": "timestamp",
        "username": "text",
        "bio": "text",
        "last_name": "text",
        "liked_object_ids": "set<uuid>"
      },
      "type_name": "",
      "table_name": "",
      "base_table": "",
      "partition_keys": [
        "id"
      ],
      "clustering_keys": [],
      "global_secondary_indexes": [
        "global_users_email_idx",
        "global_users_username_idx"
      ],
      "local_secondary_indexes": null,
      "table_options": null
    },
    "flows": {
      "fields": {
        "updated_at": "timestamp",
        "node_id": "uuid",
        "start_index": "int",
        "description_markdown": "text",
        "id": "uuid",
        "description": "text",
        "created_at": "timestamp",
        "title": "text",
        "workflow_id": "uuid",
        "step_ids": "list<uuid>"
      },
      "type_name": "",
      "table_name": "",
      "base_table": "",
      "partition_keys": [
        "node_id"
      ],
      "clustering_keys": [
        "id",
        "workflow_id"
      ],
      "global_secondary_indexes": null,
      "local_secondary_indexes": null,
      "table_options": null
    },
    "node_descendants": {
      "fields": {
        "node_id": "uuid",
        "order_index": "double",
        "id": "uuid",
        "parent_id": "uuid",
        "root_id": "uuid",
        "title": "text"
      },
      "type_name": "",
      "table_name": "",
      "base_table": "",
      "partition_keys": [
        "root_id"
      ],
      "clustering_keys": [
        "id",
        "node_id",
        "order_index"
      ],
      "global_secondary_indexes": null,
      "local_secondary_indexes": null,
      "table_options": null
    },
    "commits": {
      "fields": {
        "id": "uuid",
        "commit_type": "text",
        "contribution_request_id": "uuid",
        "created_at": "timestamp",
        "data": "map<text, text>",
        "object_id": "uuid",
        "node_id": "uuid",
        "user_id": "uuid",
        "updated_at": "timestamp"
      },
      "type_name": "",
      "table_name": "",
      "base_table": "",
      "partition_keys": [
        "contribution_request_id"
      ],
      "clustering_keys": [
        "created_at",
        "id"
      ],
      "global_secondary_indexes": null,
      "local_secondary_indexes": null,
      "table_options": null
    },
    "input_outputs": {
      "fields": {
        "updated_at": "timestamp",
        "created_at": "timestamp",
        "node_id": "uuid",
        "flow_step_id": "uuid",
        "title": "text",
        "description": "text",
        "workflow_id": "uuid",
        "value": "text",
        "data_type": "text",
        "description_markdown": "text",
        "id": "uuid",
        "original_id": "uuid",
        "root_node_id": "uuid",
        "unit": "text",
        "properties": "frozen<list<frozen<property>>>"
      },
      "type_name": "",
      "table_name": "",
      "base_table": "",
      "partition_keys": [
        "node_id"
      ],
      "clustering_keys": [
        "id",
        "workflow_id"
      ],
      "global_secondary_indexes": [
        "global_input_outputs_id_idx",
        "global_input_outputs_original_id_idx"
      ],
      "local_secondary_indexes": null,
      "table_options": null
    }
  },
  "udts": {
    "address": {
      "fields": {
        "city": "text",
        "zip": "text",
        "state": "text",
        "street": "text",
        "country": "text"
      },
      "type_name": "",
      "table_name": "",
      "base_table": "",
      "partition_keys": [],
      "clustering_keys": [],
      "global_secondary_indexes": null,
      "local_secondary_indexes": null,
      "table_options": null
    },
    "creator": {
      "fields": {
        "id": "uuid",
        "username": "text"
      },
      "type_name": "",
      "table_name": "",
      "base_table": "",
      "partition_keys": [],
      "clustering_keys": [],
      "global_secondary_indexes": null,
      "local_secondary_indexes": null,
      "table_options": null
    },
    "property": {
      "fields": {
        "value": "text",
        "data_type": "text",
        "title": "text"
      },
      "type_name": "",
      "table_name": "",
      "base_table": "",
      "partition_keys": [],
      "clustering_keys": [],
      "global_secondary_indexes": null,
      "local_secondary_indexes": null,
      "table_options": null
    },
    "owner": {
      "fields": {
        "owner_type": "text",
        "profile_image_url": "text",
        "name": "text",
        "id": "uuid",
        "username": "text"
      },
      "type_name": "",
      "table_name": "",
      "base_table": "",
      "partition_keys": [],
      "clustering_keys": [],
      "global_secondary_indexes": null,
      "local_secondary_indexes": null,
      "table_options": null
    }
  },
  "materialized_views": {
    "input_outputs_by_root_node_id": {
      "fields": {
        "original_id": "uuid",
        "id": "uuid",
        "title": "text",
        "data_type": "text",
        "workflow_id": "uuid",
        "root_node_id": "uuid",
        "unit": "text",
        "node_id": "uuid",
        "value": "text"
      },
      "type_name": "",
      "table_name": "",
      "base_table": "",
      "partition_keys": [
        "root_node_id"
      ],
      "clustering_keys": [
        "id",
        "node_id",
        "workflow_id"
      ],
      "global_secondary_indexes": null,
      "local_secondary_indexes": null,
      "table_options": null
    },
    "global_input_outputs_original_id_idx_index": {
      "fields": {
        "idx_token": "bigint",
        "node_id": "uuid",
        "original_id": "uuid",
        "workflow_id": "uuid",
        "id": "uuid"
      },
      "type_name": "",
      "table_name": "",
      "base_table": "",
      "partition_keys": [
        "original_id"
      ],
      "clustering_keys": [
        "id",
        "idx_token",
        "node_id",
        "workflow_id"
      ],
      "global_secondary_indexes": null,
      "local_secondary_indexes": null,
      "table_options": null
    },
    "global_users_username_idx_index": {
      "fields": {
        "id": "uuid",
        "idx_token": "bigint",
        "username": "text"
      },
      "type_name": "",
      "table_name": "",
      "base_table": "",
      "partition_keys": [
        "username"
      ],
      "clustering_keys": [
        "id",
        "idx_token"
      ],
      "global_secondary_indexes": null,
      "local_secondary_indexes": null,
      "table_options": null
    },
    "global_input_outputs_id_idx_index": {
      "fields": {
        "id": "uuid",
        "workflow_id": "uuid",
        "node_id": "uuid",
        "idx_token": "bigint"
      },
      "type_name": "",
      "table_name": "",
      "base_table": "",
      "partition_keys": [
        "id"
      ],
      "clustering_keys": [
        "idx_token",
        "node_id",
        "workflow_id"
      ],
      "global_secondary_indexes": null,
      "local_secondary_indexes": null,
      "table_options": null
    },
    "global_users_email_idx_index": {
      "fields": {
        "email": "text",
        "id": "uuid",
        "idx_token": "bigint"
      },
      "type_name": "",
      "table_name": "",
      "base_table": "",
      "partition_keys": [
        "email"
      ],
      "clustering_keys": [
        "id",
        "idx_token"
      ],
      "global_secondary_indexes": null,
      "local_secondary_indexes": null,
      "table_options": null
    }
  },
  "keyspace_name": "nodecosmos"
}